flask_pypprof/__init__.py
flask_pypprof/handler.py
flask_pypprof/noop_routes.py
flask_pypprof/routes.py
flask_pypprof-0.1.18.dist-info/LICENSE
flask_pypprof-0.1.18.dist-info/METADATA
flask_pypprof-0.1.18.dist-info/WHEEL
flask_pypprof-0.1.18.dist-info/RECORD
