Metadata-Version: 2.1
Name: flask-pypprof
Version: 0.1.18
Summary: Pypprof Flask wrapper
Author: Diego
Author-email: diegolparra@gmail.com
Requires-Python: >=3.8,<=3.11
Classifier: Programming Language :: Python :: 3
Classifier: Programming Language :: Python :: 3.8
Classifier: Programming Language :: Python :: 3.9
Classifier: Programming Language :: Python :: 3.10
Classifier: Programming Language :: Python :: 3.11
Requires-Dist: flask (>=2.1.3,<3.0.0)
Requires-Dist: mprofile (==0.0.15) ; sys_platform == "linux" and platform_machine == "x86_64"
Requires-Dist: protobuf (>=3.20,<4.0) ; sys_platform == "linux" and platform_machine == "x86_64"
Requires-Dist: pypprof (==0.0.1) ; sys_platform == "linux" and platform_machine == "x86_64"
Requires-Dist: zprofile (==1.0.13) ; sys_platform == "linux" and platform_machine == "x86_64"
